django3_dash-0.1.4.dist-info/licenses/LICENSE
django_dash/__init__.py
django_dash/_helpers.py
django_dash/_version.py
django_dash/admin.py
django_dash/apps.py
django_dash/logentry_admin.py
django_dash/mixins.py
django_dash/module_settings.py
django_dash/fields/__init__.py
django_dash/fields/checkbox.py
django_dash/fields/ckeditor.py
django_dash/fields/json_editor_field.py
django_dash/fields/keyvalue_field.py
django_dash/fields/summernote.py
django_dash/fields/tags_field.py
django_dash/fields/thousand_sep_field.py
django_dash/locale/ar/LC_MESSAGES/django.mo
django_dash/locale/ar/LC_MESSAGES/django.po
django_dash/locale/fa/LC_MESSAGES/django.mo
django_dash/locale/fa/LC_MESSAGES/django.po
django_dash/management/__init__.py
django_dash/management/commands/__init__.py
django_dash/management/commands/build_daisyui.py
django_dash/static/admin/css/autocomplete.css
django_dash/static/admin/css/calendar.css
django_dash/static/admin/css/customized_components.css
django_dash/static/admin/css/login.css
django_dash/static/admin/css/vendor/select2/LICENSE-SELECT2.md
django_dash/static/admin/css/vendor/select2/select2.css
django_dash/static/admin/css/vendor/select2/select2.min.css
django_dash/static/admin/fields/ckeditor_init.js
django_dash/static/admin/fields/tags.widget.js
django_dash/static/admin/fields/thousand_sep_field.js
django_dash/static/admin/fields/json-editor/json_editor_init.js
django_dash/static/admin/fields/json-editor/jsoneditor.min.js
django_dash/static/admin/fields/keyvalue_field/script.js
django_dash/static/admin/fields/keyvalue_field/style.css
django_dash/static/admin/fonts/LICENSE.txt
django_dash/static/admin/fonts/README.txt
django_dash/static/admin/fonts/Roboto-Bold-webfont.woff
django_dash/static/admin/fonts/Roboto-Light-webfont.woff
django_dash/static/admin/fonts/Roboto-Regular-webfont.woff
django_dash/static/admin/fonts/Vazir.woff2
django_dash/static/admin/fonts/Ubuntu/UFL.txt
django_dash/static/admin/fonts/Ubuntu/Ubuntu-Bold.ttf
django_dash/static/admin/fonts/Ubuntu/Ubuntu-Light.ttf
django3_dash-0.1.4.dist-info/METADATA
django3_dash-0.1.4.dist-info/WHEEL
django3_dash-0.1.4.dist-info/top_level.txt
django3_dash-0.1.4.dist-info/RECORD
