Metadata-Version: 2.4
Name: django3-dash
Version: 0.1.4
Summary: A modern Django dashboard built with DaisyUI
Author: mazen qazeh
Author-email: mazen7722 <mqazeh@gmail.com>
License: Apache-2.0
Keywords: django,admin,dashboard,daisyui,tailwindcss
Classifier: Programming Language :: Python :: 3
Classifier: License :: OSI Approved :: Apache Software License
Classifier: Operating System :: OS Independent
License-File: LICENSE
Requires-Dist: Django>=3.2
Dynamic: author
Dynamic: license-file
